[
  {
    "publishingOffice": "津地方気象台",
    "reportDatetime": "2024-12-02T17:00:00+09:00",
    "timeSeries": [
      {
        "timeDefines": [
          "2024-12-02T17:00:00+09:00",
          "2024-12-03T00:00:00+09:00",
          "2024-12-04T00:00:00+09:00"
        ],
        "areas": [
          {
            "area": {
              "name": "北中部",
              "code": "240010"
            },
            "weatherCodes": [
              "100",
              "110",
              "101"
            ],
            "weathers": [
              "晴れ",
              "晴れ　昼過ぎ　から　時々　くもり",
              "晴れ　時々　くもり"
            ],
            "winds": [
              "東の風　後　西の風",
              "西の風",
              "北西の風"
            ],
            "waves": [
              "０．５メートル",
              "０．５メートル",
              "０．５メートル"
            ]
          },
          {
            "area": {
              "name": "南部",
              "code": "240020"
            },
            "weatherCodes": [
              "100",
              "110",
              "101"
            ],
            "weathers": [
              "晴れ",
              "晴れ　昼過ぎ　から　時々　くもり",
              "晴れ　時々　くもり"
            ],
            "winds": [
              "北の風　後　南の風",
              "北の風　後　北西の風　伊勢志摩　では　後　北西の風　やや強く",
              "北の風"
            ],
            "waves": [
              "１メートル",
              "１メートル　後　１．５メートル",
              "１．５メートル"
            ]
          }
        ]
      },
      {
        "timeDefines": [
          "2024-12-02T18:00:00+09:00",
          "2024-12-03T00:00:00+09:00",
          "2024-12-03T06:00:00+09:00",
          "2024-12-03T12:00:00+09:00",
          "2024-12-03T18:00:00+09:00"
        ],
        "areas": [
          {
            "area": {
              "name": "北中部",
              "code": "240010"
            },
            "pops": [
              "0",
              "0",
              "0",
              "0",
              "10"
            ]
          },
          {
            "area": {
              "name": "南部",
              "code": "240020"
            },
            "pops": [
              "0",
              "0",
              "0",
              "0",
              "0"
            ]
          }
        ]
      },
      {
        "timeDefines": [
          "2024-12-03T00:00:00+09:00",
          "2024-12-03T09:00:00+09:00"
        ],
        "areas": [
          {
            "area": {
              "name": "津",
              "code": "53133"
            },
            "temps": [
              "7",
              "19"
            ]
          },
          {
            "area": {
              "name": "尾鷲",
              "code": "53378"
            },
            "temps": [
              "8",
              "21"
            ]
          },
          {
            "area": {
              "name": "四日市",
              "code": "53061"
            },
            "temps": [
              "5",
              "18"
            ]
          },
          {
            "area": {
              "name": "上野",
              "code": "53112"
            },
            "temps": [
              "2",
              "18"
            ]
          }
        ]
      }
    ]
  },
  {
    "publishingOffice": "津地方気象台",
    "reportDatetime": "2024-12-02T17:00:00+09:00",
    "timeSeries": [
      {
        "timeDefines": [
          "2024-12-03T00:00:00+09:00",
          "2024-12-04T00:00:00+09:00",
          "2024-12-05T00:00:00+09:00",
          "2024-12-06T00:00:00+09:00",
          "2024-12-07T00:00:00+09:00",
          "2024-12-08T00:00:00+09:00",
          "2024-12-09T00:00:00+09:00"
        ],
        "areas": [
          {
            "area": {
              "name": "三重県",
              "code": "240000"
            },
            "weatherCodes": [
              "110",
              "101",
              "101",
              "101",
              "201",
              "201",
              "101"
            ],
            "pops": [
              "",
              "10",
              "20",
              "20",
              "30",
              "30",
              "20"
            ],
            "reliabilities": [
              "",
              "",
              "A",
              "A",
              "A",
              "A",
              "A"
            ]
          }
        ]
      },
      {
        "timeDefines": [
          "2024-12-03T00:00:00+09:00",
          "2024-12-04T00:00:00+09:00",
          "2024-12-05T00:00:00+09:00",
          "2024-12-06T00:00:00+09:00",
          "2024-12-07T00:00:00+09:00",
          "2024-12-08T00:00:00+09:00",
          "2024-12-09T00:00:00+09:00"
        ],
        "areas": [
          {
            "area": {
              "name": "津",
              "code": "53133"
            },
            "tempsMin": [
              "",
              "9",
              "8",
              "6",
              "6",
              "5",
              "5"
            ],
            "tempsMinUpper": [
              "",
              "10",
              "10",
              "8",
              "8",
              "7",
              "7"
            ],
            "tempsMinLower": [
              "",
              "7",
              "6",
              "5",
              "4",
              "3",
              "3"
            ],
            "tempsMax": [
              "",
              "15",
              "14",
              "14",
              "14",
              "11",
              "12"
            ],
            "tempsMaxUpper": [
              "",
              "17",
              "16",
              "17",
              "16",
              "14",
              "14"
            ],
            "tempsMaxLower": [
              "",
              "13",
              "12",
              "12",
              "12",
              "9",
              "9"
            ]
          }
        ]
      }
    ],
    "tempAverage": {
      "areas": [
        {
          "area": {
            "name": "津",
            "code": "53133"
          },
          "min": "6.0",
          "max": "13.5"
        }
      ]
    },
    "precipAverage": {
      "areas": [
        {
          "area": {
            "name": "津",
            "code": "53133"
          },
          "min": "2.2",
          "max": "12.6"
        }
      ]
    }
  }
]